torale/__init__.py
torale/api/__init__.py
torale/api/auth.py
torale/api/clerk_auth.py
torale/api/main.py
torale/api/users.py
torale/api/routers/__init__.py
torale/api/routers/admin.py
torale/api/routers/auth.py
torale/api/routers/email_verification.py
torale/api/routers/tasks.py
torale/api/routers/templates.py
torale/api/routers/waitlist.py
torale/api/routers/webhooks.py
torale/cli/__init__.py
torale/cli/auth.py
torale/cli/main.py
torale/cli/tasks.py
torale/core/__init__.py
torale/core/config.py
torale/core/database.py
torale/core/email_verification.py
torale/core/models.py
torale/core/webhook.py
torale/executors/__init__.py
torale/executors/grounded_search.py
torale/notifications/__init__.py
torale/notifications/novu_service.py
torale/sdk/__init__.py
torale/sdk/builders.py
torale/sdk/client.py
torale/sdk/exceptions.py
torale/sdk/resources/__init__.py
torale/sdk/resources/tasks.py
torale/workers/__init__.py
torale/workers/__main__.py
torale/workers/activities.py
torale/workers/worker.py
torale/workers/workflows.py
torale-0.0.2.dist-info/METADATA
torale-0.0.2.dist-info/WHEEL
torale-0.0.2.dist-info/entry_points.txt
torale-0.0.2.dist-info/RECORD
