Metadata-Version: 2.4
Name: torale
Version: 0.0.2
Summary: Grounded search monitoring platform for AI-powered conditional automation
Project-URL: Homepage, https://torale.ai
Project-URL: Documentation, https://github.com/prasadcode/torale#readme
Project-URL: Repository, https://github.com/prasadcode/torale
Project-URL: Bug Tracker, https://github.com/prasadcode/torale/issues
Project-URL: Changelog, https://github.com/prasadcode/torale/releases
Author-email: Torale Team <hello@torale.ai>
Maintainer-email: Torale Team <hello@torale.ai>
License: MIT
Keywords: ai,automation,background-tasks,gemini,grounded-search,llm,monitoring,notifications,task-scheduler,temporal,web-scraping
Classifier: Development Status :: 4 - Beta
Classifier: Framework :: FastAPI
Classifier: Intended Audience :: Developers
Classifier: License :: OSI Approved :: MIT License
Classifier: Operating System :: OS Independent
Classifier: Programming Language :: Python :: 3
Classifier: Programming Language :: Python :: 3.11
Classifier: Programming Language :: Python :: 3.12
Classifier: Topic :: Internet :: WWW/HTTP :: Dynamic Content
Classifier: Topic :: Scientific/Engineering :: Artificial Intelligence
Classifier: Topic :: Software Development :: Libraries :: Python Modules
Classifier: Typing :: Typed
Requires-Python: >=3.11
Requires-Dist: alembic>=1.13.0
Requires-Dist: anthropic>=0.34.0
Requires-Dist: asyncpg>=0.29.0
Requires-Dist: clerk-backend-api>=1.0.0
Requires-Dist: fastapi>=0.115.0
Requires-Dist: google-genai>=0.3.0
Requires-Dist: grpcio>=1.76.0
Requires-Dist: httpx>=0.27.0
Requires-Dist: novu-py>=1.3.0
Requires-Dist: openai>=1.45.0
Requires-Dist: psycopg2-binary>=2.9.0
Requires-Dist: pydantic-settings>=2.4.0
Requires-Dist: pydantic[email]>=2.9.0
Requires-Dist: python-dotenv>=1.0.0
Requires-Dist: rich>=13.7.0
Requires-Dist: sqlalchemy>=2.0.0
Requires-Dist: temporalio>=1.7.0
Requires-Dist: typer>=0.12.0
Requires-Dist: uvicorn[standard]>=0.30.0
Provides-Extra: dev
Requires-Dist: pytest-asyncio>=0.24.0; extra == 'dev'
Requires-Dist: pytest-cov>=5.0.0; extra == 'dev'
Requires-Dist: pytest>=8.3.0; extra == 'dev'
Requires-Dist: ruff>=0.6.0; extra == 'dev'
Provides-Extra: research
Requires-Dist: langfuse>=2.0.0; extra == 'research'
